pydantic_cwe/__init__.py
pydantic_cwe/loader.py
pydantic_cwe/py.typed
pydantic_cwe/models/__init__.py
pydantic_cwe/models/catalog.py
pydantic_cwe/models/common.py
pydantic_cwe/models/categories/__init__.py
pydantic_cwe/models/categories/category.py
pydantic_cwe/models/weaknesses/__init__.py
pydantic_cwe/models/weaknesses/weakness.py
pydantic_cwe-0.1.2.dist-info/licenses/LICENSE
pydantic_cwe-0.1.2.dist-info/METADATA
pydantic_cwe-0.1.2.dist-info/WHEEL
pydantic_cwe-0.1.2.dist-info/top_level.txt
pydantic_cwe-0.1.2.dist-info/RECORD
