Metadata-Version: 2.4
Name: pydantic-cwe
Version: 0.1.2
Summary: A Pythonic representation of CWE records using Pydantic models.
Author-email: Eduard Pinconschi <eduard.pinconschi@tecnico.ulisboa.pt>
License-Expression: MIT
Project-URL: repository, https://github.com/epicosy/pydantic-cwe
Project-URL: homepage, https://github.com/epicosy/pydantic-cwe
Keywords: package,cwe,pydantic
Classifier: Topic :: Software Development
Classifier: Programming Language :: Python
Classifier: Environment :: Console
Classifier: Intended Audience :: Developers
Requires-Python: >=3.9
License-File: LICENSE
Requires-Dist: lxml>=5.4.0
Requires-Dist: pydantic>=2.11.6
Provides-Extra: test
Requires-Dist: pytest; extra == "test"
Requires-Dist: pytest-cov; extra == "test"
Requires-Dist: coverage; extra == "test"
Requires-Dist: twine>=1.11.0; extra == "test"
Requires-Dist: setuptools>=38.6.0; extra == "test"
Requires-Dist: wheel>=0.31.0; extra == "test"
Dynamic: license-file
